<annotation>
	<folder>vat</folder>
	<filename>3200181130_17040089_20180516.jpg</filename>
	<path>/home/adam/Pictures/vat/3200181130_17040089_20180516.jpg</path>
	<source>
		<database>Unknown</database>
	</source>
	<size>
		<width>2624</width>
		<height>1617</height>
		<depth>3</depth>
	</size>
	<segmented>0</segmented>
	<object>
		<name>code</name>
		<pose>Unspecified</pose>
		<truncated>0</truncated>
		<difficult>0</difficult>
		<bndbox>
			<xmin>409</xmin>
			<ymin>117</ymin>
			<xmax>824</xmax>
			<ymax>180</ymax>
		</bndbox>
	</object>
	<object>
		<name>number</name>
		<pose>Unspecified</pose>
		<truncated>0</truncated>
		<difficult>0</difficult>
		<bndbox>
			<xmin>1927</xmin>
			<ymin>108</ymin>
			<xmax>2292</xmax>
			<ymax>179</ymax>
		</bndbox>
	</object>
	<object>
		<name>date</name>
		<pose>Unspecified</pose>
		<truncated>0</truncated>
		<difficult>0</difficult>
		<bndbox>
			<xmin>2205</xmin>
			<ymin>254</ymin>
			<xmax>2512</xmax>
			<ymax>303</ymax>
		</bndbox>
	</object>
	<object>
		<name>buyer</name>
		<pose>Unspecified</pose>
		<truncated>0</truncated>
		<difficult>0</difficult>
		<bndbox>
			<xmin>607</xmin>
			<ymin>360</ymin>
			<xmax>1552</xmax>
			<ymax>591</ymax>
		</bndbox>
	</object>
	<object>
		<name>seller</name>
		<pose>Unspecified</pose>
		<truncated>0</truncated>
		<difficult>0</difficult>
		<bndbox>
			<xmin>597</xmin>
			<ymin>1235</ymin>
			<xmax>1553</xmax>
			<ymax>1451</ymax>
		</bndbox>
	</object>
</annotation>
