<annotation>
	<folder>vat</folder>
	<filename>3600164130_02509918_20171214.jpg</filename>
	<path>/home/adam/Pictures/vat/3600164130_02509918_20171214.jpg</path>
	<source>
		<database>Unknown</database>
	</source>
	<size>
		<width>3488</width>
		<height>2530</height>
		<depth>1</depth>
	</size>
	<segmented>0</segmented>
	<object>
		<name>code</name>
		<pose>Unspecified</pose>
		<truncated>0</truncated>
		<difficult>0</difficult>
		<bndbox>
			<xmin>1189</xmin>
			<ymin>265</ymin>
			<xmax>1588</xmax>
			<ymax>344</ymax>
		</bndbox>
	</object>
	<object>
		<name>number</name>
		<pose>Unspecified</pose>
		<truncated>0</truncated>
		<difficult>0</difficult>
		<bndbox>
			<xmin>2622</xmin>
			<ymin>317</ymin>
			<xmax>2959</xmax>
			<ymax>400</ymax>
		</bndbox>
	</object>
	<object>
		<name>date</name>
		<pose>Unspecified</pose>
		<truncated>0</truncated>
		<difficult>0</difficult>
		<bndbox>
			<xmin>2811</xmin>
			<ymin>457</ymin>
			<xmax>3111</xmax>
			<ymax>507</ymax>
		</bndbox>
	</object>
	<object>
		<name>buyer</name>
		<pose>Unspecified</pose>
		<truncated>0</truncated>
		<difficult>0</difficult>
		<bndbox>
			<xmin>1292</xmin>
			<ymin>492</ymin>
			<xmax>2266</xmax>
			<ymax>753</ymax>
		</bndbox>
	</object>
	<object>
		<name>seller</name>
		<pose>Unspecified</pose>
		<truncated>0</truncated>
		<difficult>0</difficult>
		<bndbox>
			<xmin>1255</xmin>
			<ymin>1343</ymin>
			<xmax>2224</xmax>
			<ymax>1573</ymax>
		</bndbox>
	</object>
</annotation>
