<annotation>
	<folder>vat</folder>
	<filename>4100164130_03591157_20171230.jpg</filename>
	<path>/home/adam/Pictures/vat/4100164130_03591157_20171230.jpg</path>
	<source>
		<database>Unknown</database>
	</source>
	<size>
		<width>2530</width>
		<height>3500</height>
		<depth>1</depth>
	</size>
	<segmented>0</segmented>
	<object>
		<name>code</name>
		<pose>Unspecified</pose>
		<truncated>0</truncated>
		<difficult>0</difficult>
		<bndbox>
			<xmin>446</xmin>
			<ymin>407</ymin>
			<xmax>798</xmax>
			<ymax>467</ymax>
		</bndbox>
	</object>
	<object>
		<name>number</name>
		<pose>Unspecified</pose>
		<truncated>0</truncated>
		<difficult>0</difficult>
		<bndbox>
			<xmin>1765</xmin>
			<ymin>379</ymin>
			<xmax>2081</xmax>
			<ymax>439</ymax>
		</bndbox>
	</object>
	<object>
		<name>date</name>
		<pose>Unspecified</pose>
		<truncated>0</truncated>
		<difficult>0</difficult>
		<bndbox>
			<xmin>1943</xmin>
			<ymin>505</ymin>
			<xmax>2229</xmax>
			<ymax>537</ymax>
		</bndbox>
	</object>
	<object>
		<name>seller</name>
		<pose>Unspecified</pose>
		<truncated>0</truncated>
		<difficult>0</difficult>
		<bndbox>
			<xmin>548</xmin>
			<ymin>1358</ymin>
			<xmax>1442</xmax>
			<ymax>1535</ymax>
		</bndbox>
	</object>
	<object>
		<name>code</name>
		<pose>Unspecified</pose>
		<truncated>0</truncated>
		<difficult>0</difficult>
		<bndbox>
			<xmin>453</xmin>
			<ymin>1800</ymin>
			<xmax>815</xmax>
			<ymax>1856</ymax>
		</bndbox>
	</object>
	<object>
		<name>number</name>
		<pose>Unspecified</pose>
		<truncated>0</truncated>
		<difficult>0</difficult>
		<bndbox>
			<xmin>1775</xmin>
			<ymin>1790</ymin>
			<xmax>2096</xmax>
			<ymax>1847</ymax>
		</bndbox>
	</object>
	<object>
		<name>date</name>
		<pose>Unspecified</pose>
		<truncated>0</truncated>
		<difficult>0</difficult>
		<bndbox>
			<xmin>1953</xmin>
			<ymin>1903</ymin>
			<xmax>2237</xmax>
			<ymax>1942</ymax>
		</bndbox>
	</object>
	<object>
		<name>buyer</name>
		<pose>Unspecified</pose>
		<truncated>0</truncated>
		<difficult>0</difficult>
		<bndbox>
			<xmin>566</xmin>
			<ymin>1990</ymin>
			<xmax>1441</xmax>
			<ymax>2178</ymax>
		</bndbox>
	</object>
</annotation>
